secret_key_generator/__init__.py
secret_key_generator/generator_class.py
secret_key_generator/properties.py
secret_key_generator/secret_key_generator.py
secret_key_generator-0.0.8.dist-info/LICENSE
secret_key_generator-0.0.8.dist-info/METADATA
secret_key_generator-0.0.8.dist-info/WHEEL
secret_key_generator-0.0.8.dist-info/top_level.txt
secret_key_generator-0.0.8.dist-info/RECORD
