Metadata-Version: 2.1
Name: secret-key-generator
Version: 0.0.8
Summary: Package for secret key generation in Django framework.
Home-page: https://github.com/PickBas/django_secret_key_generator
Author: Kirill Sayed
Author-email: sayed.kirill@gmail.com
License: UNKNOWN
Platform: UNKNOWN
Classifier: Programming Language :: Python :: 3
Classifier: License :: OSI Approved :: MIT License
Classifier: Operating System :: OS Independent
Requires-Python: >=3.6
